[
  {
    "id": "0",
    "name": "춘천 송암 스포츠타운 주 경기장",
    "team": "강원",
    "maxPerson": 18156,
    "addr": "강원도 춘천시 스포츠타운길 136"
  },
  {
    "id": "1",
    "name": "창원 축구 센터",
    "team": "경남",
    "maxPerson": 15116,
    "addr": "경남 창원시 성산구 비음로 97"
  },
  {
    "id": "2",
    "name": "DGB 대구은행 파크",
    "team": "대구",
    "maxPerson": 12415,
    "addr": "대구 북구 고성로 191"
  },
  {
    "id": "3",
    "name": "상주 시민 운동장",
    "team": "상주",
    "maxPerson": 15042,
    "addr": "경북 상주시 북상주로 24-7"
  },
  {
    "id": "4",
    "name": "서울 월드컵 경기장",
    "team": "서울",
    "maxPerson": 66704,
    "addr": "서울특별시 마포구 월드컵로 240"
  },
  {
    "id": "5",
    "name": "탄천 종합 운동장 주 경기장",
    "team": "성남",
    "maxPerson": 16146,
    "addr": "경기도 성남시 분당구 탄천로 215"
  },
  {
    "id": "6",
    "name": "수원 월드컵 경기장",
    "team": "수원",
    "maxPerson": 44031,
    "addr": "경기도 수원시 팔달구 월드컵로 310"
  },
  {
    "id": "7",
    "name": "울산 문수 축구 경기장",
    "team": "울산",
    "maxPerson": 43554,
    "addr": "울산광역시 남구 문수로 44"
  },
  {
    "id": "8",
    "name": "인천 축구 전용 경기장",
    "team": "인천",
    "maxPerson": 20300,
    "addr": "인천광역시 중구 참외전로 246"
  },
  {
    "id": "9",
    "name": "전주 월드컵 경기장",
    "team": "전북",
    "maxPerson": 42477,
    "addr": "전라북도 전주시 덕진구 기린대로 1055"
  },
  {
    "id": "10",
    "name": "제주 월드컵 경기장",
    "team": "제주",
    "maxPerson": 29791,
    "addr": "제주특별자치도 서귀포시 월드컵로 33"
  },
  {
    "id": "11",
    "name": "포항 스틸야드",
    "team": "포항",
    "maxPerson": 17443,
    "addr": "경상북도 포항시 남구 동해안로6213번길 20"
  }
]
